{"train": [{"start_alert": 15, "end_alert": 15, "start_entities": [8, 2, 3, 9, 16, 12, 4, 11], "end_entities": [1], "shortest_alert_path": [15]}, {"start_alert": 15, "end_alert": 14, "start_entities": [16], "end_entities": [13], "shortest_alert_path": [15, 8, 14]}, {"start_alert": 10, "end_alert": 14, "start_entities": [1, 2, 3, 4, 8, 9, 11, 12, 13], "end_entities": [7], "shortest_alert_path": [10, 13, 14]}, {"start_alert": 0, "end_alert": 0, "start_entities": [8, 4, 2, 9, 7, 1, 3], "end_entities": [6], "shortest_alert_path": [0]}], "test": [{"start_alert": 14, "end_alert": 10, "start_entities": [6, 7], "end_entities": [2], "shortest_alert_path": [14, 13, 10]}, {"start_alert": 14, "end_alert": 14, "start_entities": [11, 9, 6, 8, 12, 1, 3, 4, 7, 2], "end_entities": [13], "shortest_alert_path": [14]}, {"start_alert": 0, "end_alert": 14, "start_entities": [5], "end_entities": [13], "shortest_alert_path": [0, 3, 14]}, {"start_alert": 14, "end_alert": 15, "start_entities": [6, 7, 13], "end_entities": [16], "shortest_alert_path": [14, 8, 15]}, {"start_alert": 0, "end_alert": 10, "start_entities": [5, 6, 7], "end_entities": [13], "shortest_alert_path": [0, 4, 10]}, {"start_alert": 10, "end_alert": 0, "start_entities": [11, 12, 13], "end_entities": [5], "shortest_alert_path": [10, 8, 0]}, {"start_alert": 0, "end_alert": 15, "start_entities": [5, 6, 7], "end_entities": [16], "shortest_alert_path": [0, 4, 15]}, {"start_alert": 10, "end_alert": 15, "start_entities": [13], "end_entities": [16], "shortest_alert_path": [10, 8, 15]}, {"start_alert": 14, "end_alert": 0, "start_entities": [11, 12, 13], "end_entities": [5], "shortest_alert_path": [14, 6, 0]}, {"start_alert": 15, "end_alert": 10, "start_entities": [16], "end_entities": [13], "shortest_alert_path": [15, 8, 10]}, {"start_alert": 15, "end_alert": 0, "start_entities": [11, 12, 16], "end_entities": [5], "shortest_alert_path": [15, 8, 0]}, {"start_alert": 10, "end_alert": 10, "start_entities": [4, 8, 9, 13, 3, 12, 2, 11], "end_entities": [1], "shortest_alert_path": [10]}], "score": 0}